dcvideo/__init__.py
dcvideo/_message.py
dcvideo/_object.py
dcvideo/_result.py
dcvideo/_youban.py
dcvideo/alioss.py
dcvideo/config.py
dcvideo/export.py
dcvideo/publish.py
dcvideo/utils.py
dcvideo/web.py
dcvideo-1.1.2.dist-info/METADATA
dcvideo-1.1.2.dist-info/WHEEL
dcvideo-1.1.2.dist-info/entry_points.txt
dcvideo-1.1.2.dist-info/top_level.txt
dcvideo-1.1.2.dist-info/RECORD
