Metadata-Version: 2.1
Name: dcvideo
Version: 1.1.2
Summary: UNKNOWN
Home-page: https://www.shortvideo.work
Author: netfere
Author-email: netfere@gmail.com
License: UNKNOWN
Platform: UNKNOWN
Requires-Python: >=3.7
Requires-Dist: requests (==2.28.1)
Requires-Dist: requests-toolbelt (==0.9.1)
Requires-Dist: cos-python-sdk-v5 (==1.9.21)
Requires-Dist: fake-useragent (==1.1.1)
Requires-Dist: flask (==2.2.3)
Requires-Dist: flask-cors (==3.0.10)
Requires-Dist: oss2 (==2.16.0)
